.project
.pydevproject
AUTHORS.txt
LICENSE.txt
Make.mm
README.txt
distribute.sh
fix_setuptools_chmod.py
setup.cfg
setup.py
setup_sample.py
update.py
.settings/org.eclipse.core.resources.prefs
branches/matter-usedsawmodel/Atom.py
branches/matter-usedsawmodel/AtomLoader2.py
branches/matter-usedsawmodel/AtomicObject.py
branches/matter-usedsawmodel/Lattice.py
branches/matter-usedsawmodel/Make.mm
branches/matter-usedsawmodel/PDFFitStructure.py
branches/matter-usedsawmodel/Site.py
branches/matter-usedsawmodel/SpaceGroups.py
branches/matter-usedsawmodel/Structure.py
branches/matter-usedsawmodel/StructureErrors.py
branches/matter-usedsawmodel/StructureManipulator.py
branches/matter-usedsawmodel/SymmetryUtilities.py
branches/matter-usedsawmodel/UnitCell.py
branches/matter-usedsawmodel/__init__.py
branches/matter-usedsawmodel/properties.py
branches/matter-usedsawmodel/sgtbxspacegroups.py
branches/matter-usedsawmodel/utils.py
branches/matter-usedsawmodel/version.py
branches/matter-usedsawmodel/wyckoff.py
branches/matter-usedsawmodel/ChemicalElements/ChemicalElements.py
branches/matter-usedsawmodel/ChemicalElements/Make.mm
branches/matter-usedsawmodel/ChemicalElements/__init__.py
branches/matter-usedsawmodel/ChemicalElements/covalent_radius.py
branches/matter-usedsawmodel/ChemicalElements/cpk_color.py
branches/matter-usedsawmodel/ChemicalElements/crystal_structure.py
branches/matter-usedsawmodel/ChemicalElements/magneticmoment.py
branches/matter-usedsawmodel/ChemicalElements/mass.py
branches/matter-usedsawmodel/ChemicalElements/name.py
branches/matter-usedsawmodel/ChemicalElements/symbol.py
branches/matter-usedsawmodel/Parsers/Make.mm
branches/matter-usedsawmodel/Parsers/P_auto.py
branches/matter-usedsawmodel/Parsers/P_bratoms.py
branches/matter-usedsawmodel/Parsers/P_cif.py
branches/matter-usedsawmodel/Parsers/P_pdb.py
branches/matter-usedsawmodel/Parsers/P_pdffit.py
branches/matter-usedsawmodel/Parsers/P_rawxyz.py
branches/matter-usedsawmodel/Parsers/P_xcfg.py
matter.egg-info/PKG-INFO
matter.egg-info/SOURCES.txt
matter.egg-info/dependency_links.txt
matter.egg-info/requires.txt
matter.egg-info/top_level.txt
