Metadata-Version: 1.0
Name: matter
Version: 0.8-r960-20110308
Summary: matter classes and parsers for structure formats
Home-page: http://dev.danse.us/trac/inelastic/wiki/crystal
Author: J. Brandon Keith
Author-email: jbrkeith@gmail.edu
License: BSD
Download-URL: http://dev.danse.us/packages/
Keywords: matter material crystal structure symmetry
Platform: UNKNOWN
Classifier: Development Status :: 4 - Beta
Classifier: Environment :: Console
Classifier: Intended Audience :: Science/Research
Classifier: Operating System :: MacOS
Classifier: Operating System :: Microsoft :: Windows
Classifier: Operating System :: POSIX
Classifier: Programming Language :: Python :: 2.6
Classifier: Topic :: Scientific/Engineering :: Physics
